pythreadserver/__init__.py
pythreadserver/client.py
pythreadserver/constants.py
pythreadserver/server.py
pythreadserver/textlog.py
pythreadserver-0.1.3.dist-info/METADATA
pythreadserver-0.1.3.dist-info/WHEEL
pythreadserver-0.1.3.dist-info/top_level.txt
pythreadserver-0.1.3.dist-info/RECORD
