Metadata-Version: 2.1
Name: pythreadserver
Version: 0.1.3
Summary: Socket-based server package
Author: rain1107
Author-email: ryanbays@icloud.com
Keywords: python,socket,threading
Classifier: Development Status :: 1 - Planning
Classifier: Intended Audience :: Developers
Classifier: Programming Language :: Python :: 3
Classifier: Operating System :: Unix
Classifier: Operating System :: MacOS :: MacOS X
Classifier: Operating System :: Microsoft :: Windows
